tsc/__init__.py
tsc/algo.pyx
tsc/converter.pyx
tsc/counter.pxd
tsc/counter.pyx
tsc/khash.pxd
tsc/paq.pyx
tsc/paq.pyxbld
tsc/replaces.pyx
tsc/klib/khash.h
tsc/klib/khash_python.h
tsc/klib/ktypes.h
tsc/klib/kvec.h
tsc/paq9a/paq9a.hpp
tsc-0.3.3.dist-info/DESCRIPTION.rst
tsc-0.3.3.dist-info/METADATA
tsc-0.3.3.dist-info/RECORD
tsc-0.3.3.dist-info/WHEEL
tsc-0.3.3.dist-info/metadata.json
tsc-0.3.3.dist-info/top_level.txt
